{
  "$schema": "https://developer.microsoft.com/json-schemas/fabric/item/report/definition/page/2.0.0/schema.json",
  "name": "60269a73141469b06603",
  "displayName": "Activity Completion Progress",
  "displayOption": "FitToPage",
  "height": 1080,
  "width": 1920,
  "filterConfig": {
    "filters": [
      {
        "name": "ecbffbe5dea251a5e217",
        "field": {
          "Column": {
            "Expression": {
              "SourceRef": {
                "Entity": "01 XER_TASK"
              }
            },
            "Property": "TaskType_Classified"
          }
        },
        "type": "Categorical",
        "filter": {
          "Version": 2,
          "From": [
            {
              "Name": "0",
              "Entity": "01 XER_TASK",
              "Type": 0
            }
          ],
          "Where": [
            {
              "Condition": {
                "In": {
                  "Expressions": [
                    {
                      "Column": {
                        "Expression": {
                          "SourceRef": {
                            "Source": "0"
                          }
                        },
                        "Property": "TaskType_Classified"
                      }
                    }
                  ],
                  "Values": [
                    [
                      {
                        "Literal": {
                          "Value": "'Activity'"
                        }
                      }
                    ]
                  ]
                }
              }
            }
          ]
        },
        "howCreated": "User"
      }
    ]
  },
  "objects": {
    "background": [
      {
        "properties": {
          "color": {
            "solid": {
              "color": {
                "expr": {
                  "ThemeDataColor": {
                    "ColorId": 0,
                    "Percent": -0.1
                  }
                }
              }
            }
          },
          "transparency": {
            "expr": {
              "Literal": {
                "Value": "0D"
              }
            }
          },
          "image": {
            "image": {
              "name": {
                "expr": {
                  "Literal": {
                    "Value": "'Contract Background.png'"
                  }
                }
              },
              "url": {
                "expr": {
                  "ResourcePackageItem": {
                    "PackageName": "RegisteredResources",
                    "PackageType": 1,
                    "ItemName": "Contract_Background1603920230288043.png"
                  }
                }
              },
              "scaling": {
                "expr": {
                  "Literal": {
                    "Value": "'Fit'"
                  }
                }
              }
            }
          }
        }
      }
    ],
    "displayArea": [
      {
        "properties": {
          "verticalAlignment": {
            "expr": {
              "Literal": {
                "Value": "'Middle'"
              }
            }
          }
        }
      }
    ]
  },
  "visualInteractions": [
    {
      "source": "c8145b1f8b1c2246ee50",
      "target": "49e78e73ffa150d909c0",
      "type": "NoFilter"
    }
  ]
}